{
  "title": "Departments with More Than 5 Employees",
  "difficulty": "Easy",
  "description": "Write a SQL query to count employees in each department having more than 5 employees.",
  "schema": "CREATE TABLE employees (id INTEGER, name TEXT, department_id INTEGER);\nINSERT INTO employees VALUES (1, 'Alice', 10);\nINSERT INTO employees VALUES (2, 'Bob', 10);\nINSERT INTO employees VALUES (3, 'Charlie', 20);\nINSERT INTO employees VALUES (4, 'David', 10);",
  "expectedResult": {
    "columns": [
      "department_id",
      "num_employees"
    ],
    "values": []
  },
  "hint": "Use GROUP BY department_id and HAVING COUNT(*) > 5.",
  "contributor": {
    "name": "Linkedin",
    "link": "https://linkedin.com/"
  }
}